{
  "name": "Node.js Dev Container",
  "dockerComposeFile": ["../docker-compose.yml"],
  "service": "app",
  "workspaceFolder": "/app",
  "forwardPorts": [3000, 9229],
  "postCreateCommand": "npm install",
  "customizations": {
    "vscode": {
      "extensions": [
        "dbaeumer.vscode-eslint",
        "esbenp.prettier-vscode",
        "ms-vscode.vscode-typescript-next"
      ],
      "settings": {
        "editor.formatOnSave": true,
        "terminal.integrated.shell.linux": "/bin/bash"
      }
    }
  }
}
